NikeyiTongling/Dockerfile
NikeyiTongling/README.md
NikeyiTongling/__init__.py
NikeyiTongling/__main__.py
NikeyiTongling/file.epub
NikeyiTongling/index.html
NikeyiTongling/css/__init__.py
NikeyiTongling/css/annotations.css
NikeyiTongling/css/main.css
NikeyiTongling/css/normalize.css
NikeyiTongling/css/popup.css
NikeyiTongling/font/__init__.py
NikeyiTongling/font/fontello.eot
NikeyiTongling/font/fontello.svg
NikeyiTongling/font/fontello.ttf
NikeyiTongling/font/fontello.woff
NikeyiTongling/img/__init__.py
NikeyiTongling/img/annotator-glyph-sprite.png
NikeyiTongling/img/annotator-icon-sprite.png
NikeyiTongling/img/apple-touch-icon.png
NikeyiTongling/img/cancelfullscreen.png
NikeyiTongling/img/close.png
NikeyiTongling/img/fullscreen.png
NikeyiTongling/img/loader.gif
NikeyiTongling/img/menu-icon.png
NikeyiTongling/img/save.png
NikeyiTongling/img/saved.png
NikeyiTongling/img/settings-s.png
NikeyiTongling/img/settings.png
NikeyiTongling/img/star.png
NikeyiTongling/js/__init__.py
NikeyiTongling/js/epub.js
NikeyiTongling/js/epub.min.js
NikeyiTongling/js/epub.min.map
NikeyiTongling/js/hooks.min.js
NikeyiTongling/js/hooks.min.map
NikeyiTongling/js/reader.js
NikeyiTongling/js/reader.js.map
NikeyiTongling/js/reader.min.js
NikeyiTongling/js/reader.min.map
NikeyiTongling/js/hooks/__init__.py
NikeyiTongling/js/hooks/extensions/__init__.py
NikeyiTongling/js/hooks/extensions/highlight.js
NikeyiTongling/js/libs/__init__.py
NikeyiTongling/js/libs/jquery.min.js
NikeyiTongling/js/libs/localforage.min.js
NikeyiTongling/js/libs/screenfull.js
NikeyiTongling/js/libs/screenfull.min.js
NikeyiTongling/js/libs/zip.min.js
NikeyiTongling/js/plugins/__init__.py
NikeyiTongling/js/plugins/hypothesis.js
NikeyiTongling/js/plugins/search.js
nikeyi_tongling-2022.10.3.0.dist-info/METADATA
nikeyi_tongling-2022.10.3.0.dist-info/WHEEL
nikeyi_tongling-2022.10.3.0.dist-info/entry_points.txt
nikeyi_tongling-2022.10.3.0.dist-info/top_level.txt
nikeyi_tongling-2022.10.3.0.dist-info/RECORD
